<?xml version="1.0" encoding="UTF-8"?>
<!DOCTYPE mapper PUBLIC "-//mybatis.org//DTD Mapper 3.0//EN" "http://mybatis.org/dtd/mybatis-3-mapper.dtd">
<mapper namespace="org.iscas.tj2.pyt.springboot_mybatis.dao.VarProjectRelationMapper">
  <resultMap id="BaseResultMap" type="org.iscas.tj2.pyt.springboot_mybatis.domain.VarProjectRelation">
    <!--
      WARNING - @mbg.generated
      This element is automatically generated by MyBatis Generator, do not modify.
      This element was generated on Mon Dec 03 18:53:01 CST 2018.
    -->
    <constructor>
      <idArg column="Id_VarProjectRelation" javaType="java.lang.Integer" jdbcType="INTEGER" />
      <arg column="Id_Var" javaType="java.lang.Integer" jdbcType="INTEGER" />
      <arg column="Id_Project" javaType="java.lang.Integer" jdbcType="INTEGER" />
    </constructor>
  </resultMap>
  <sql id="Base_Column_List">
    <!--
      WARNING - @mbg.generated
      This element is automatically generated by MyBatis Generator, do not modify.
      This element was generated on Mon Dec 03 18:53:01 CST 2018.
    -->
    Id_VarProjectRelation, Id_Var, Id_Project
  </sql>
  <select id="selectByPrimaryKey" parameterType="java.lang.Integer" resultMap="BaseResultMap">
    <!--
      WARNING - @mbg.generated
      This element is automatically generated by MyBatis Generator, do not modify.
      This element was generated on Mon Dec 03 18:53:01 CST 2018.
    -->
    select 
    <include refid="Base_Column_List" />
    from VarProjectRelation
    where Id_VarProjectRelation = #{idVarprojectrelation,jdbcType=INTEGER}
  </select>
  <delete id="deleteByPrimaryKey" parameterType="java.lang.Integer">
    <!--
      WARNING - @mbg.generated
      This element is automatically generated by MyBatis Generator, do not modify.
      This element was generated on Mon Dec 03 18:53:01 CST 2018.
    -->
    delete from VarProjectRelation
    where Id_VarProjectRelation = #{idVarprojectrelation,jdbcType=INTEGER}
  </delete>
  <insert id="insert" parameterType="org.iscas.tj2.pyt.springboot_mybatis.domain.VarProjectRelation">
    <!--
      WARNING - @mbg.generated
      This element is automatically generated by MyBatis Generator, do not modify.
      This element was generated on Mon Dec 03 18:53:01 CST 2018.
    -->
    insert into VarProjectRelation (Id_VarProjectRelation, Id_Var, Id_Project
      )
    values (#{idVarprojectrelation,jdbcType=INTEGER}, #{idVar,jdbcType=INTEGER}, #{idProject,jdbcType=INTEGER}
      )
  </insert>
  <insert id="insertSelective" parameterType="org.iscas.tj2.pyt.springboot_mybatis.domain.VarProjectRelation" useGeneratedKeys="true" keyProperty="idVarprojectrelation">
    <!--
      WARNING - @mbg.generated
      This element is automatically generated by MyBatis Generator, do not modify.
      This element was generated on Mon Dec 03 18:53:01 CST 2018.
    -->
    insert into VarProjectRelation
    <trim prefix="(" suffix=")" suffixOverrides=",">
      <if test="idVarprojectrelation != null">
        Id_VarProjectRelation,
      </if>
      <if test="idVar != null">
        Id_Var,
      </if>
      <if test="idProject != null">
        Id_Project,
      </if>
    </trim>
    <trim prefix="values (" suffix=")" suffixOverrides=",">
      <if test="idVarprojectrelation != null">
        #{idVarprojectrelation,jdbcType=INTEGER},
      </if>
      <if test="idVar != null">
        #{idVar,jdbcType=INTEGER},
      </if>
      <if test="idProject != null">
        #{idProject,jdbcType=INTEGER},
      </if>
    </trim>
  </insert>
  <update id="updateByPrimaryKeySelective" parameterType="org.iscas.tj2.pyt.springboot_mybatis.domain.VarProjectRelation">
    <!--
      WARNING - @mbg.generated
      This element is automatically generated by MyBatis Generator, do not modify.
      This element was generated on Mon Dec 03 18:53:01 CST 2018.
    -->
    update VarProjectRelation
    <set>
      <if test="idVar != null">
        Id_Var = #{idVar,jdbcType=INTEGER},
      </if>
      <if test="idProject != null">
        Id_Project = #{idProject,jdbcType=INTEGER},
      </if>
    </set>
    where Id_VarProjectRelation = #{idVarprojectrelation,jdbcType=INTEGER}
  </update>
  <update id="updateByPrimaryKey" parameterType="org.iscas.tj2.pyt.springboot_mybatis.domain.VarProjectRelation">
    <!--
      WARNING - @mbg.generated
      This element is automatically generated by MyBatis Generator, do not modify.
      This element was generated on Mon Dec 03 18:53:01 CST 2018.
    -->
    update VarProjectRelation
    set Id_Var = #{idVar,jdbcType=INTEGER},
      Id_Project = #{idProject,jdbcType=INTEGER}
    where Id_VarProjectRelation = #{idVarprojectrelation,jdbcType=INTEGER}
  </update>
</mapper>